notdiamond/__init__.py
notdiamond/_base_client.py
notdiamond/_client.py
notdiamond/_compat.py
notdiamond/_constants.py
notdiamond/_exceptions.py
notdiamond/_files.py
notdiamond/_models.py
notdiamond/_qs.py
notdiamond/_resource.py
notdiamond/_response.py
notdiamond/_streaming.py
notdiamond/_types.py
notdiamond/_version.py
notdiamond/py.typed
notdiamond/_utils/__init__.py
notdiamond/_utils/_compat.py
notdiamond/_utils/_datetime_parse.py
notdiamond/_utils/_json.py
notdiamond/_utils/_logs.py
notdiamond/_utils/_proxy.py
notdiamond/_utils/_reflection.py
notdiamond/_utils/_resources_proxy.py
notdiamond/_utils/_streams.py
notdiamond/_utils/_sync.py
notdiamond/_utils/_transform.py
notdiamond/_utils/_typing.py
notdiamond/_utils/_utils.py
notdiamond/lib/.keep
notdiamond/resources/__init__.py
notdiamond/resources/custom_router.py
notdiamond/resources/model_router.py
notdiamond/resources/models.py
notdiamond/resources/preferences.py
notdiamond/resources/prompt_optimization.py
notdiamond/types/__init__.py
notdiamond/types/custom_router_train_custom_router_params.py
notdiamond/types/custom_router_train_custom_router_response.py
notdiamond/types/golden_record_param.py
notdiamond/types/job_status.py
notdiamond/types/model.py
notdiamond/types/model_list_params.py
notdiamond/types/model_list_response.py
notdiamond/types/model_router_select_model_params.py
notdiamond/types/model_router_select_model_response.py
notdiamond/types/preference_create_params.py
notdiamond/types/preference_create_response.py
notdiamond/types/preference_update_params.py
notdiamond/types/prompt_optimization_get_optimization_results_response.py
notdiamond/types/prompt_optimization_get_optimziation_status_response.py
notdiamond/types/prompt_optimization_optimize_params.py
notdiamond/types/prompt_optimization_optimize_response.py
notdiamond/types/prompt_optimization_retrieve_costs_response.py
notdiamond/types/request_provider_param.py
notdiamond-1.5.0.dist-info/METADATA
notdiamond-1.5.0.dist-info/WHEEL
notdiamond-1.5.0.dist-info/licenses/LICENSE
notdiamond-1.5.0.dist-info/RECORD
